ff/__init__.py
ffmetadata_py-2.0.0.dist-info/LICENSE
ffmetadata_py-2.0.0.dist-info/METADATA
ffmetadata_py-2.0.0.dist-info/WHEEL
ffmetadata_py-2.0.0.dist-info/top_level.txt
ffmetadata_py-2.0.0.dist-info/RECORD
