Metadata-Version: 2.1
Name: ffmetadata-py
Version: 2.0.0
Summary: Python wrapper for The Fragile Families Metadata API
Home-page: https://github.com/fragilefamilieschallenge/ffmetadata-py
Author: Alex Kindel, Vineet Bansal
Author-email: akindel@princeton.edu, vineetb@princeton.edu
Classifier: Programming Language :: Python :: 3
Classifier: License :: OSI Approved :: MIT License
Classifier: Operating System :: OS Independent
License-File: LICENSE
Requires-Dist: simplejson
Requires-Dist: requests
